Cosmic/__init__.py
Cosmic/cosmiclogger.py
Cosmic/uwulogger.py
Cosmic_2-0.0.1.dist-info/METADATA
Cosmic_2-0.0.1.dist-info/WHEEL
Cosmic_2-0.0.1.dist-info/top_level.txt
Cosmic_2-0.0.1.dist-info/RECORD
